./.env.example
./.gitignore
./LICENSE
./PKG-INFO
./README.md
./pyproject.toml
./requirements.txt
./server.json
./server.py
slack_mcp_server_v2-0.1.0.dist-info/METADATA
slack_mcp_server_v2-0.1.0.dist-info/WHEEL
slack_mcp_server_v2-0.1.0.dist-info/entry_points.txt
slack_mcp_server_v2-0.1.0.dist-info/licenses/LICENSE
slack_mcp_server_v2-0.1.0.dist-info/RECORD
