Metadata-Version: 2.4
Name: slack-mcp-server-v2
Version: 0.1.0
Summary: MCP server for reading Slack conversations and threads
Project-URL: Homepage, https://github.com/stevenvo/slack-mcp-server
Project-URL: Repository, https://github.com/stevenvo/slack-mcp-server
Project-URL: Issues, https://github.com/stevenvo/slack-mcp-server/issues
Author-email: Steven Vo <findme@stevenvo.info>
License: MIT
License-File: LICENSE
Keywords: ai,llm,mcp,model-context-protocol,slack
Classifier: Development Status :: 4 - Beta
Classifier: Intended Audience :: Developers
Classifier: License :: OSI Approved :: MIT License
Classifier: Programming Language :: Python :: 3
Classifier: Programming Language :: Python :: 3.10
Classifier: Programming Language :: Python :: 3.11
Classifier: Programming Language :: Python :: 3.12
Requires-Python: >=3.10
Requires-Dist: mcp>=1.0.0
Requires-Dist: python-dotenv>=1.0.0
Requires-Dist: slack-sdk>=3.35.0
